{
  "info": {
    "name": "Walle QEAA Dictionary API",
    "_postman_id": "eb6d3a19-bc0e-42cb-92d3-a0d0ecb3884e",
    "description": "Collection pour tester les APIs QEAA (types, data, datasets). Variables: baseUrl, typeId, dataId, datasetId.",
    "schema": "https://schema.getpostman.com/json/collection/v2.1.0/collection.json"
  },
  "variable": [
    {
      "key": "baseUrl",
      "value": "http://localhost:8080"
    },
    {
      "key": "typeId",
      "value": ""
    },
    {
      "key": "dataId",
      "value": ""
    },
    {
      "key": "datasetId",
      "value": ""
    }
  ],
  "item": [
    {
      "name": "QEAA Types",
      "item": [
        {
          "name": "Create Type",
          "request": {
            "method": "POST",
            "header": [
              {
                "key": "Content-Type",
                "value": "application/json"
              }
            ],
            "url": {
              "raw": "{{baseUrl}}/api/v1/dictionary/qeaa/types",
              "host": [
                "{{baseUrl}}"
              ],
              "path": [
                "api",
                "v1",
                "dictionary",
                "qeaa",
                "types"
              ]
            },
            "body": {
              "mode": "raw",
              "raw": "{\n  \"name\": \"TYPE_EXAMPLE\"\n}"
            }
          },
          "event": [
            {
              "listen": "test",
              "script": {
                "type": "text/javascript",
                "exec": [
                  "pm.test('Status is 201', function () { pm.response.to.have.status(201); });",
                  "const json = pm.response.json();",
                  "pm.environment.set('typeId', json.id);",
                  "pm.test('typeId saved', function () { pm.expect(pm.environment.get('typeId')).to.be.ok; });"
                ]
              }
            }
          ]
        },
        {
          "name": "List Types",
          "request": {
            "method": "GET",
            "url": {
              "raw": "{{baseUrl}}/api/v1/dictionary/qeaa/types",
              "host": [
                "{{baseUrl}}"
              ],
              "path": [
                "api",
                "v1",
                "dictionary",
                "qeaa",
                "types"
              ]
            }
          },
          "event": [
            {
              "listen": "test",
              "script": {
                "type": "text/javascript",
                "exec": [
                  "pm.test('Status is 200', function () { pm.response.to.have.status(200); });"
                ]
              }
            }
          ]
        },
        {
          "name": "Update Type (by typeId)",
          "request": {
            "method": "PUT",
            "header": [
              {
                "key": "Content-Type",
                "value": "application/json"
              }
            ],
            "url": {
              "raw": "{{baseUrl}}/api/v1/dictionary/qeaa/types/{{typeId}}",
              "host": [
                "{{baseUrl}}"
              ],
              "path": [
                "api",
                "v1",
                "dictionary",
                "qeaa",
                "types",
                "{{typeId}}"
              ]
            },
            "body": {
              "mode": "raw",
              "raw": "{\n  \"name\": \"TYPE_EXAMPLE_UPDATED\"\n}"
            }
          },
          "event": [
            {
              "listen": "test",
              "script": {
                "type": "text/javascript",
                "exec": [
                  "pm.test('Status is 200', function () { pm.response.to.have.status(200); });"
                ]
              }
            }
          ]
        },
        {
          "name": "Delete Type (by typeId)",
          "request": {
            "method": "DELETE",
            "url": {
              "raw": "{{baseUrl}}/api/v1/dictionary/qeaa/types/{{typeId}}",
              "host": [
                "{{baseUrl}}"
              ],
              "path": [
                "api",
                "v1",
                "dictionary",
                "qeaa",
                "types",
                "{{typeId}}"
              ]
            }
          },
          "event": [
            {
              "listen": "test",
              "script": {
                "type": "text/javascript",
                "exec": [
                  "pm.test('Status is 204', function () { pm.response.to.have.status(204); });"
                ]
              }
            }
          ]
        }
      ]
    },
    {
      "name": "QEAA Data",
      "item": [
        {
          "name": "Create Data",
          "request": {
            "method": "POST",
            "header": [
              {
                "key": "Content-Type",
                "value": "application/json"
              }
            ],
            "url": {
              "raw": "{{baseUrl}}/api/v1/dictionary/qeaa/data",
              "host": [
                "{{baseUrl}}"
              ],
              "path": [
                "api",
                "v1",
                "dictionary",
                "qeaa",
                "data"
              ]
            },
            "body": {
              "mode": "raw",
              "raw": "{\n  \"name\": \"DATA_EXAMPLE\"\n}"
            }
          },
          "event": [
            {
              "listen": "test",
              "script": {
                "type": "text/javascript",
                "exec": [
                  "pm.test('Status is 201', function () { pm.response.to.have.status(201); });",
                  "const json = pm.response.json();",
                  "pm.environment.set('dataId', json.id);",
                  "pm.test('dataId saved', function () { pm.expect(pm.environment.get('dataId')).to.be.ok; });"
                ]
              }
            }
          ]
        },
        {
          "name": "List Data",
          "request": {
            "method": "GET",
            "url": {
              "raw": "{{baseUrl}}/api/v1/dictionary/qeaa/data",
              "host": [
                "{{baseUrl}}"
              ],
              "path": [
                "api",
                "v1",
                "dictionary",
                "qeaa",
                "data"
              ]
            }
          },
          "event": [
            {
              "listen": "test",
              "script": {
                "type": "text/javascript",
                "exec": [
                  "pm.test('Status is 200', function () { pm.response.to.have.status(200); });"
                ]
              }
            }
          ]
        },
        {
          "name": "Update Data (by dataId)",
          "request": {
            "method": "PUT",
            "header": [
              {
                "key": "Content-Type",
                "value": "application/json"
              }
            ],
            "url": {
              "raw": "{{baseUrl}}/api/v1/dictionary/qeaa/data/{{dataId}}",
              "host": [
                "{{baseUrl}}"
              ],
              "path": [
                "api",
                "v1",
                "dictionary",
                "qeaa",
                "data",
                "{{dataId}}"
              ]
            },
            "body": {
              "mode": "raw",
              "raw": "{\n  \"name\": \"DATA_EXAMPLE_UPDATED\"\n}"
            }
          },
          "event": [
            {
              "listen": "test",
              "script": {
                "type": "text/javascript",
                "exec": [
                  "pm.test('Status is 200', function () { pm.response.to.have.status(200); });"
                ]
              }
            }
          ]
        },
        {
          "name": "Delete Data (by dataId)",
          "request": {
            "method": "DELETE",
            "url": {
              "raw": "{{baseUrl}}/api/v1/dictionary/qeaa/data/{{dataId}}",
              "host": [
                "{{baseUrl}}"
              ],
              "path": [
                "api",
                "v1",
                "dictionary",
                "qeaa",
                "data",
                "{{dataId}}"
              ]
            }
          },
          "event": [
            {
              "listen": "test",
              "script": {
                "type": "text/javascript",
                "exec": [
                  "pm.test('Status is 204', function () { pm.response.to.have.status(204); });"
                ]
              }
            }
          ]
        }
      ]
    },
    {
      "name": "QEAA Datasets",
      "item": [
        {
          "name": "Create Dataset (needs typeId & dataId)",
          "request": {
            "method": "POST",
            "header": [
              {
                "key": "Content-Type",
                "value": "application/json"
              }
            ],
            "url": {
              "raw": "{{baseUrl}}/api/v1/dictionary/qeaa/datasets",
              "host": [
                "{{baseUrl}}"
              ],
              "path": [
                "api",
                "v1",
                "dictionary",
                "qeaa",
                "datasets"
              ]
            },
            "body": {
              "mode": "raw",
              "raw": "{\n  \"name\": \"DATASET_EXAMPLE\",\n  \"typeId\": \"{{typeId}}\",\n  \"dataId\": \"{{dataId}}\"\n}"
            }
          },
          "event": [
            {
              "listen": "test",
              "script": {
                "type": "text/javascript",
                "exec": [
                  "pm.test('Status is 201', function () { pm.response.to.have.status(201); });",
                  "const json = pm.response.json();",
                  "pm.environment.set('datasetId', json.id);",
                  "pm.test('datasetId saved', function () { pm.expect(pm.environment.get('datasetId')).to.be.ok; });"
                ]
              }
            }
          ]
        },
        {
          "name": "List Datasets",
          "request": {
            "method": "GET",
            "url": {
              "raw": "{{baseUrl}}/api/v1/dictionary/qeaa/datasets",
              "host": [
                "{{baseUrl}}"
              ],
              "path": [
                "api",
                "v1",
                "dictionary",
                "qeaa",
                "datasets"
              ]
            }
          },
          "event": [
            {
              "listen": "test",
              "script": {
                "type": "text/javascript",
                "exec": [
                  "pm.test('Status is 200', function () { pm.response.to.have.status(200); });"
                ]
              }
            }
          ]
        },
        {
          "name": "Update Dataset (by datasetId)",
          "request": {
            "method": "PUT",
            "header": [
              {
                "key": "Content-Type",
                "value": "application/json"
              }
            ],
            "url": {
              "raw": "{{baseUrl}}/api/v1/dictionary/qeaa/datasets/{{datasetId}}",
              "host": [
                "{{baseUrl}}"
              ],
              "path": [
                "api",
                "v1",
                "dictionary",
                "qeaa",
                "datasets",
                "{{datasetId}}"
              ]
            },
            "body": {
              "mode": "raw",
              "raw": "{\n  \"name\": \"DATASET_EXAMPLE_UPDATED\",\n  \"typeId\": \"{{typeId}}\",\n  \"dataId\": \"{{dataId}}\"\n}"
            }
          },
          "event": [
            {
              "listen": "test",
              "script": {
                "type": "text/javascript",
                "exec": [
                  "pm.test('Status is 200', function () { pm.response.to.have.status(200); });"
                ]
              }
            }
          ]
        },
        {
          "name": "Delete Dataset (by datasetId)",
          "request": {
            "method": "DELETE",
            "url": {
              "raw": "{{baseUrl}}/api/v1/dictionary/qeaa/datasets/{{datasetId}}",
              "host": [
                "{{baseUrl}}"
              ],
              "path": [
                "api",
                "v1",
                "dictionary",
                "qeaa",
                "datasets",
                "{{datasetId}}"
              ]
            }
          },
          "event": [
            {
              "listen": "test",
              "script": {
                "type": "text/javascript",
                "exec": [
                  "pm.test('Status is 204', function () { pm.response.to.have.status(204); });"
                ]
              }
            }
          ]
        }
      ]
    }
  ]
}